{
  "status": "done",
  "assets": {
    "main-4a2244ea28f99ebcc07c.min.css": {
      "name": "main-4a2244ea28f99ebcc07c.min.css",
      "path": "/Users/nbudak/src/geniza/sitemedia/bundles/main-4a2244ea28f99ebcc07c.min.css",
      "publicPath": "/static/bundles/main-4a2244ea28f99ebcc07c.min.css"
    },
    "main-4a2244ea28f99ebcc07c.min.js": {
      "name": "main-4a2244ea28f99ebcc07c.min.js",
      "path": "/Users/nbudak/src/geniza/sitemedia/bundles/main-4a2244ea28f99ebcc07c.min.js",
      "publicPath": "/static/bundles/main-4a2244ea28f99ebcc07c.min.js"
    }
  },
  "chunks": {
    "main": [
      "main-4a2244ea28f99ebcc07c.min.css",
      "main-4a2244ea28f99ebcc07c.min.js"
    ]
  },
  "publicPath": "/static/bundles/"
}